{"cameraMode":{"drawMode":0,"name":"Shaded","section":"Shading Mode"},"sceneLighting":true,"audioPlay":false,"sceneViewState":{"showFog":true,"showMaterialUpdate":false,"showSkybox":true,"showFlares":true,"showImageEffects":true,"showParticleSystems":true},"in2DMode":false,"pivot":{"x":-3.6957778930664064,"y":12.146831512451172,"z":-1.327946662902832},"rotation":{"x":-0.19948601722717286,"y":0.7961100339889526,"z":-0.3543848395347595,"w":-0.4481368064880371},"size":24.555049896240236,"orthographic":false}